hackerargs/__init__.py
hackerargs/argparse_access.py
hackerargs/args.py
hackerargs/strict_bool_yaml.py
hackerargs-1.1.1.dist-info/LICENSE
hackerargs-1.1.1.dist-info/METADATA
hackerargs-1.1.1.dist-info/WHEEL
hackerargs-1.1.1.dist-info/top_level.txt
hackerargs-1.1.1.dist-info/RECORD
