Metadata-Version: 2.1
Name: hackerargs
Version: 1.1.1
Summary: Easy config system, minimizing new lines of code
Author: Max Shen
Project-URL: Homepage, https://github.com/maxwshen/hackerargs
Project-URL: Issues, https://github.com/maxwshen/hackerargs/issues
License-File: LICENSE
Requires-Dist: PyYAML
